XarrayActive/__init__.py
XarrayActive/active_chunk.py
XarrayActive/active_dask.py
XarrayActive/active_xarray.py
XarrayActive/backend.py
XarrayActive/datastore.py
XarrayActive/wrappers.py
XarrayActive-2024.9.0.dist-info/LICENSE
XarrayActive-2024.9.0.dist-info/METADATA
XarrayActive-2024.9.0.dist-info/WHEEL
XarrayActive-2024.9.0.dist-info/entry_points.txt
XarrayActive-2024.9.0.dist-info/top_level.txt
XarrayActive-2024.9.0.dist-info/RECORD
