Metadata-Version: 2.1
Name: XarrayActive
Version: 2024.9.0
Summary: Xarray Backend Engine to enable the PyActiveStorage Python Package
Author-email: Daniel Westwood <daniel.westwood@stfc.ac.uk>
License: BSD 3-Clause License
Keywords: active,xarray,XarrayActive,ArrayPartition
Requires-Python: >=3.7
License-File: LICENSE
Requires-Dist: scipy==1.12.0
Requires-Dist: xarray==2024.6.0
Requires-Dist: cfdm==1.11.1.0
Requires-Dist: netCDF4==1.6.5
Requires-Dist: h5py==3.11.0
Requires-Dist: dask==2024.7.0
Requires-Dist: cftime==1.6.4
Requires-Dist: cfunits==3.3.7
Requires-Dist: pytest==7.2.0
Requires-Dist: ArrayPartition==1.0.1
